DalineUnit/DalBase.pyc
DalineUnit/DalBaseTU.pyc
DalineUnit/DalBaseUnit.pyc
DalineUnit/DalConf.pyc
DalineUnit/DalDecorate.pyc
DalineUnit/DalDevTool.pyc
DalineUnit/DalGenScript.pyc
DalineUnit/DalGit.pyc
DalineUnit/DalGitoliteParser.pyc
DalineUnit/DalLogIn.pyc
DalineUnit/DalOSS.pyc
DalineUnit/DalUploadUnit.pyc
DalineUnit/DesignFile.pyc
DalineUnit/GenTestData.pyc
DalineUnit/MysqlOper.pyc
DalineUnit/OracleOper.pyc
DalineUnit/Template.pyc
DalineUnit/TemplateAgent.pyc
DalineUnit/__init__.py
DalineUnit/__init__.pyc
DalineUnit/dalconf.ini
DalineUnit/puwrapper_pb2.pyc
DalineUnit/puwrapper_pb2_grpc.pyc
DalineUnit/src/DalBaseUnit.h
DalineUnit/src/libDalBaseUnit.so
DalineUnit/src/rapidjson/allocators.h
DalineUnit/src/rapidjson/cursorstreamwrapper.h
DalineUnit/src/rapidjson/document.h
DalineUnit/src/rapidjson/encodedstream.h
DalineUnit/src/rapidjson/encodings.h
DalineUnit/src/rapidjson/filereadstream.h
DalineUnit/src/rapidjson/filewritestream.h
DalineUnit/src/rapidjson/fwd.h
DalineUnit/src/rapidjson/istreamwrapper.h
DalineUnit/src/rapidjson/memorybuffer.h
DalineUnit/src/rapidjson/memorystream.h
DalineUnit/src/rapidjson/ostreamwrapper.h
DalineUnit/src/rapidjson/pointer.h
DalineUnit/src/rapidjson/prettywriter.h
DalineUnit/src/rapidjson/rapidjson.h
DalineUnit/src/rapidjson/reader.h
DalineUnit/src/rapidjson/schema.h
DalineUnit/src/rapidjson/stream.h
DalineUnit/src/rapidjson/stringbuffer.h
DalineUnit/src/rapidjson/writer.h
DalineUnit/src/rapidjson/error/en.h
DalineUnit/src/rapidjson/error/error.h
DalineUnit/src/rapidjson/internal/biginteger.h
DalineUnit/src/rapidjson/internal/clzll.h
DalineUnit/src/rapidjson/internal/diyfp.h
DalineUnit/src/rapidjson/internal/dtoa.h
DalineUnit/src/rapidjson/internal/ieee754.h
DalineUnit/src/rapidjson/internal/itoa.h
DalineUnit/src/rapidjson/internal/meta.h
DalineUnit/src/rapidjson/internal/pow10.h
DalineUnit/src/rapidjson/internal/regex.h
DalineUnit/src/rapidjson/internal/stack.h
DalineUnit/src/rapidjson/internal/strfunc.h
DalineUnit-0.0.69.dist-info/LICENSE
DalineUnit-0.0.69.dist-info/METADATA
DalineUnit-0.0.69.dist-info/WHEEL
DalineUnit-0.0.69.dist-info/entry_points.txt
DalineUnit-0.0.69.dist-info/top_level.txt
DalineUnit-0.0.69.dist-info/RECORD
